the_incredible_test_of_mufraggi/__init__.py
the_incredible_test_of_mufraggi/core.py
the_incredible_test_of_mufraggi-0.1.4.dist-info/METADATA
the_incredible_test_of_mufraggi-0.1.4.dist-info/WHEEL
the_incredible_test_of_mufraggi-0.1.4.dist-info/RECORD
