Metadata-Version: 2.1
Name: the_incredible_test_of_mufraggi
Version: 0.1.4
Summary: it is a test
Author: hugomufraggi
Author-email: hugo.mufraggi@epitech.eu
Requires-Python: >=3.12,<4.0
Classifier: Programming Language :: Python :: 3
Classifier: Programming Language :: Python :: 3.12
Requires-Dist: pymongo (>=4.8.0,<5.0.0)
